Metadata-Version: 1.0
Name: dci
Version: 0.0.2
Summary: An alternative client for the distributed-ci.io
Home-page: https://github.com/goneri/python-dci
Author: Gonéri Le Bouder
Author-email: goneri@lebouder.net
License: Apache v2.0
Platform: UNKNOWN
